summarize_gutenberg/__init__.py
summarize_gutenberg/__main__.py
summarize_gutenberg/api.py
summarize_gutenberg/cli.py
summarize_gutenberg/db.py
summarize_gutenberg/demo.py
summarize_gutenberg/get_books.py
summarize_gutenberg/get_text.py
summarize_gutenberg/make_summary.py
summarize_gutenberg-0.0.35.dist-info/METADATA
summarize_gutenberg-0.0.35.dist-info/WHEEL
summarize_gutenberg-0.0.35.dist-info/entry_points.txt
summarize_gutenberg-0.0.35.dist-info/licenses/LICENSE
summarize_gutenberg-0.0.35.dist-info/RECORD
