Metadata-Version: 2.3
Name: summarize_gutenberg
Version: 0.0.35
Summary: Generate abstractive summaries of Project Gutenberg tests
Project-URL: Homepage, https://github.com/jwjacobson/summarize
Project-URL: Issues, https://github.com/jwjacobson/summarize/issues
Author-email: Jeff Jacobson <jeffjacobsonhimself@gmail.com>
License:                     GNU GENERAL PUBLIC LICENSE
License-File: LICENSE
Keywords: LLM,Pegasus,abstractive summary,books,literature
Classifier: Development Status :: 3 - Alpha
Classifier: Environment :: Console
Classifier: Intended Audience :: Developers
Classifier: Intended Audience :: Education
Classifier: Intended Audience :: End Users/Desktop
Classifier: License :: OSI Approved :: GNU General Public License v3 (GPLv3)
Classifier: Natural Language :: English
Classifier: Operating System :: OS Independent
Classifier: Programming Language :: Python
Classifier: Programming Language :: Python :: 3
Classifier: Programming Language :: Python :: 3 :: Only
Classifier: Programming Language :: Python :: 3.12
Classifier: Topic :: Internet
Classifier: Topic :: Internet :: WWW/HTTP
Classifier: Topic :: Other/Nonlisted Topic
Classifier: Topic :: Terminals :: Terminal Emulators/X Terminals
Classifier: Topic :: Text Processing :: Linguistic
Requires-Python: >=3.12
Requires-Dist: requests
Requires-Dist: rich
Requires-Dist: tinydb
Requires-Dist: torch
Requires-Dist: transformers
Requires-Dist: typer
Provides-Extra: test
Requires-Dist: pytest; extra == 'test'
Requires-Dist: pytest-cov; extra == 'test'
Provides-Extra: tools
Requires-Dist: pre-commit; extra == 'tools'
Requires-Dist: ruff; extra == 'tools'
